poinc/__init__.py
poinc/job2poinc.cp39-win_amd64.pyd
poinc/job_request.py
poinc-0.1.2.dist-info/LICENSE
poinc-0.1.2.dist-info/METADATA
poinc-0.1.2.dist-info/WHEEL
poinc-0.1.2.dist-info/top_level.txt
poinc-0.1.2.dist-info/RECORD
